ccsds-0.1.0b20.dist-info/METADATA
ccsds-0.1.0b20.dist-info/WHEEL
ccsds-0.1.0b20.dist-info/licenses/LICENSE.txt
ccsds/__init__.py
ccsds/__init__.pyi
ccsds/py.typed
ccsds/ccsds.cpython-311-x86_64-linux-gnu.so
ccsds-0.1.0b20.dist-info/RECORD
