Metadata-Version: 2.4
Name: ccsds
Version: 0.1.0b20
Classifier: Development Status :: 4 - Beta
Classifier: Programming Language :: Python
Classifier: Intended Audience :: Developers
Classifier: License :: OSI Approved :: GNU General Public License v3 or later (GPLv3+)
Requires-Dist: pytest ; extra == 'test'
Provides-Extra: test
License-File: LICENSE.txt
Keywords: ccsds,spacepacket,framing,cadu
Author: Bruce Flynn <brucef@ssec.wisc.edu>
Author-email: Bruce Flynn <brucef@ssec.wisc.edu>
Requires-Python: >=3.9
Project-URL: Source Code, https://github.com/bmflynn/ccsds-rs
